{
  "InicioData": {
    "Destacados": [
      {
        "Titulo": "FaceApp, ¿Un Peligro Para Nuestros Datos?",
        "Descripcion": "",
        "Imagen": "../../img.png",
        "autor": "Jesus 1"
      },
      {
        "Titulo": "ACÁ ENTRE NOS… La Violencia",
        "Descripcion": "",
        "Imagen": "../../img.png",
        "autor": "Jesus 2"
      },
      {
        "Titulo": "ACÁ ENTRE NOS… El Maíz Nuestro De Cada Día",
        "Descripcion": "",
        "Imagen": "../../img.png",
        "autor": "Jesus 2"
      }
    ],
    "Recomendados": [
      {
        "Titulo": "Hola",
        "Descripcion": "",
        "Imagen": "../../img.png",
        "autor": "Jesus"
      },
      {
        "Titulo": "Hola",
        "Descripcion": "",
        "Imagen": "../../img.png",
        "autor": "Jesus"
      },
      {
        "Titulo": "Hola",
        "Descripcion": "",
        "Imagen": "../../img.png",
        "autor": "Jesus"
      }
    ]
  }
}
